ibm_watson_machine_learning/Set.py
ibm_watson_machine_learning/__init__.py
ibm_watson_machine_learning/assets.py
ibm_watson_machine_learning/client.py
ibm_watson_machine_learning/connections.py
ibm_watson_machine_learning/deployments.py
ibm_watson_machine_learning/experiments.py
ibm_watson_machine_learning/export_assets.py
ibm_watson_machine_learning/factsheets.py
ibm_watson_machine_learning/functions.py
ibm_watson_machine_learning/hpo.py
ibm_watson_machine_learning/href_definitions.py
ibm_watson_machine_learning/hw_spec.py
ibm_watson_machine_learning/import_assets.py
ibm_watson_machine_learning/instance.py
ibm_watson_machine_learning/instance_new_plan.py
ibm_watson_machine_learning/lifecycle.py
ibm_watson_machine_learning/metanames.py
ibm_watson_machine_learning/migration_v4ga_cloud.py
ibm_watson_machine_learning/model_definition.py
ibm_watson_machine_learning/models.py
ibm_watson_machine_learning/party_wrapper.py
ibm_watson_machine_learning/pipelines.py
ibm_watson_machine_learning/pkg_extn.py
ibm_watson_machine_learning/platform_spaces.py
ibm_watson_machine_learning/remote_training_system.py
ibm_watson_machine_learning/repository.py
ibm_watson_machine_learning/runtimes.py
ibm_watson_machine_learning/script.py
ibm_watson_machine_learning/shiny.py
ibm_watson_machine_learning/spaces.py
ibm_watson_machine_learning/sw_spec.py
ibm_watson_machine_learning/task_credentials.py
ibm_watson_machine_learning/training.py
ibm_watson_machine_learning/volumes.py
ibm_watson_machine_learning/wml_client_error.py
ibm_watson_machine_learning/wml_resource.py
ibm_watson_machine_learning/_wrappers/__init__.py
ibm_watson_machine_learning/_wrappers/requests.py
ibm_watson_machine_learning/data_loaders/__init__.py
ibm_watson_machine_learning/data_loaders/experiment.py
ibm_watson_machine_learning/data_loaders/datasets/__init__.py
ibm_watson_machine_learning/data_loaders/datasets/experiment.py
ibm_watson_machine_learning/deployment/__init__.py
ibm_watson_machine_learning-1.0.367.dist-info/LICENSE.txt
ibm_watson_machine_learning-1.0.367.dist-info/METADATA
ibm_watson_machine_learning-1.0.367.dist-info/WHEEL
ibm_watson_machine_learning-1.0.367.dist-info/top_level.txt
ibm_watson_machine_learning-1.0.367.dist-info/RECORD
