Metadata-Version: 2.1
Name: ibm_watson_machine_learning
Version: 1.0.367
Summary: IBM Watson Machine Learning API Client
Home-page: https://ibm.github.io/watson-machine-learning-sdk
Author: IBM
Author-email: lukasz.cmielowski@pl.ibm.com, dorota.laczak@ibm.com
License: BSD-3-Clause
Keywords: watson,machine learning,IBM,Bluemix,client,API,IBM Cloud
Classifier: Development Status :: 5 - Production/Stable
Classifier: Natural Language :: English
Classifier: License :: OSI Approved :: BSD License
Classifier: Programming Language :: Python :: 3.10
Classifier: Operating System :: MacOS :: MacOS X
Classifier: Operating System :: POSIX :: Linux
Classifier: Operating System :: Microsoft :: Windows
Classifier: Intended Audience :: Science/Research
Classifier: Intended Audience :: Developers
Classifier: Intended Audience :: Information Technology
Classifier: Topic :: Software Development :: Libraries
Classifier: Topic :: Software Development :: Libraries :: Python Modules
Classifier: Topic :: Scientific/Engineering :: Artificial Intelligence
Classifier: Topic :: Scientific/Engineering :: Information Analysis
Classifier: Topic :: Internet
Requires-Python: >=3.10,<3.13
License-File: LICENSE.txt
Requires-Dist: requests
Requires-Dist: urllib3
Requires-Dist: pandas<2.2.0,>=0.24.2
Requires-Dist: certifi
Requires-Dist: lomond
Requires-Dist: tabulate
Requires-Dist: packaging
Requires-Dist: ibm-cos-sdk<2.14.0,>=2.12.0
Requires-Dist: importlib-metadata
Provides-Extra: fl-rt23-1-py3-10
Requires-Dist: tensorflow==2.12.0; extra == "fl-rt23-1-py3-10"
Requires-Dist: scikit-learn==1.1.1; extra == "fl-rt23-1-py3-10"
Requires-Dist: torch==2.0.0; extra == "fl-rt23-1-py3-10"
Requires-Dist: numpy==1.23.5; extra == "fl-rt23-1-py3-10"
Requires-Dist: pandas==1.5.3; extra == "fl-rt23-1-py3-10"
Requires-Dist: pytest==6.2.5; extra == "fl-rt23-1-py3-10"
Requires-Dist: pyYAML==6.0.1; extra == "fl-rt23-1-py3-10"
Requires-Dist: parse==1.19.0; extra == "fl-rt23-1-py3-10"
Requires-Dist: websockets==10.1; extra == "fl-rt23-1-py3-10"
Requires-Dist: requests==2.31.0; extra == "fl-rt23-1-py3-10"
Requires-Dist: scipy==1.10.1; extra == "fl-rt23-1-py3-10"
Requires-Dist: environs==9.5.0; extra == "fl-rt23-1-py3-10"
Requires-Dist: pathlib2==2.3.6; extra == "fl-rt23-1-py3-10"
Requires-Dist: diffprivlib==0.5.1; extra == "fl-rt23-1-py3-10"
Requires-Dist: numcompress==0.1.2; extra == "fl-rt23-1-py3-10"
Requires-Dist: psutil; extra == "fl-rt23-1-py3-10"
Requires-Dist: setproctitle; extra == "fl-rt23-1-py3-10"
Requires-Dist: tabulate==0.8.9; extra == "fl-rt23-1-py3-10"
Requires-Dist: lz4; extra == "fl-rt23-1-py3-10"
Requires-Dist: gym; extra == "fl-rt23-1-py3-10"
Requires-Dist: image==1.5.33; extra == "fl-rt23-1-py3-10"
Requires-Dist: ddsketch==2.0.4; extra == "fl-rt23-1-py3-10"
Requires-Dist: skorch==0.12.0; extra == "fl-rt23-1-py3-10"
Requires-Dist: protobuf==4.22.1; extra == "fl-rt23-1-py3-10"
Requires-Dist: GPUtil; extra == "fl-rt23-1-py3-10"
Requires-Dist: joblib==1.1.1; extra == "fl-rt23-1-py3-10"
Requires-Dist: skops==0.9.0; extra == "fl-rt23-1-py3-10"
Requires-Dist: msgpack==1.0.7; extra == "fl-rt23-1-py3-10"
Requires-Dist: msgpack-numpy==0.4.8; extra == "fl-rt23-1-py3-10"
Requires-Dist: cryptography==39.0.1; extra == "fl-rt23-1-py3-10"
Provides-Extra: fl-crypto
Requires-Dist: pyhelayers==1.5.0.3; extra == "fl-crypto"
